RiskLabAI/__init__.py
RiskLabAI/backtest/__init__.py
RiskLabAI/backtest/backtest_overfitting_simulation.py
RiskLabAI/backtest/backtest_statistics.py
RiskLabAI/backtest/backtest_synthetic_data.py
RiskLabAI/backtest/bet_sizing.py
RiskLabAI/backtest/probabilistic_sharpe_ratio.py
RiskLabAI/backtest/probability_of_backtest_overfitting.py
RiskLabAI/backtest/strategy_risk.py
RiskLabAI/backtest/test_set_overfitting.py
RiskLabAI/backtest/validation/__init__.py
RiskLabAI/backtest/validation/adaptive_combinatorial_purged.py
RiskLabAI/backtest/validation/bagged_combinatorial_purged.py
RiskLabAI/backtest/validation/combinatorial_purged.py
RiskLabAI/backtest/validation/cross_validator_controller.py
RiskLabAI/backtest/validation/cross_validator_factory.py
RiskLabAI/backtest/validation/cross_validator_interface.py
RiskLabAI/backtest/validation/kfold.py
RiskLabAI/backtest/validation/purged_kfold.py
RiskLabAI/backtest/validation/walk_forward.py
RiskLabAI/cluster/__init__.py
RiskLabAI/cluster/clustering.py
RiskLabAI/controller/__init__.py
RiskLabAI/controller/bars_initializer.py
RiskLabAI/controller/data_structure_controller.py
RiskLabAI/data/__init__.py
RiskLabAI/data/denoise/__init__.py
RiskLabAI/data/denoise/denoising.py
RiskLabAI/data/differentiation/__init__.py
RiskLabAI/data/differentiation/differentiation.py
RiskLabAI/data/distance/__init__.py
RiskLabAI/data/distance/distance_metric.py
RiskLabAI/data/labeling/__init__.py
RiskLabAI/data/labeling/financial_labels.py
RiskLabAI/data/labeling/labeling.py
RiskLabAI/data/structures/__init__.py
RiskLabAI/data/structures/abstract_bars.py
RiskLabAI/data/structures/abstract_imbalance_bars.py
RiskLabAI/data/structures/abstract_information_driven_bars.py
RiskLabAI/data/structures/abstract_run_bars.py
RiskLabAI/data/structures/imbalance_bars.py
RiskLabAI/data/structures/run_bars.py
RiskLabAI/data/structures/standard_bars.py
RiskLabAI/data/structures/time_bars.py
RiskLabAI/data/synthetic_data/__init__.py
risklabai-1.0.7.dist-info/licenses/LICENSE
risklabai-1.0.7.dist-info/METADATA
risklabai-1.0.7.dist-info/WHEEL
risklabai-1.0.7.dist-info/entry_points.txt
risklabai-1.0.7.dist-info/top_level.txt
risklabai-1.0.7.dist-info/RECORD
