Metadata-Version: 2.4
Name: RiskLabAI
Version: 1.0.7
Summary: Financial AI using Python, based on 'Advances in Financial Machine Learning' and 'Machine Learning for Asset Managers'.
Author-email: RiskLab <arian@risklab.ai>
License: BSD 3-Clause License
Project-URL: Homepage, https://github.com/RiskLabAI/RiskLabAI.py
Project-URL: Bug Tracker, https://github.com/RiskLabAI/RiskLabAI.py/issues
Project-URL: Changelog, https://github.com/RiskLabAI/RiskLabAI.py/releases
Keywords: finance,machine learning,quantitative finance,fintech,de prado,backtesting
Classifier: Programming Language :: Python :: 3
Classifier: License :: OSI Approved :: BSD License
Classifier: Intended Audience :: Developers
Classifier: Intended Audience :: Financial and Insurance Industry
Classifier: Intended Audience :: Science/Research
Classifier: Operating System :: OS Independent
Classifier: Topic :: Office/Business :: Financial
Classifier: Topic :: Scientific/Engineering :: Artificial Intelligence
Requires-Python: >=3.9
License-File: LICENSE
Requires-Dist: numpy
Requires-Dist: pandas
Requires-Dist: scipy
Requires-Dist: scikit-learn
Requires-Dist: statsmodels
Requires-Dist: numba
Requires-Dist: joblib
Requires-Dist: ta
Provides-Extra: pde
Requires-Dist: torch; extra == "pde"
Provides-Extra: synth
Requires-Dist: quantecon; extra == "synth"
Provides-Extra: plot
Requires-Dist: matplotlib; extra == "plot"
Requires-Dist: seaborn; extra == "plot"
Requires-Dist: plotly; extra == "plot"
Provides-Extra: dev
Requires-Dist: yfinance; extra == "dev"
Requires-Dist: memory_profiler; extra == "dev"
Requires-Dist: jupyterlab; extra == "dev"
Requires-Dist: stable-baselines3; extra == "dev"
Requires-Dist: gymnasium; extra == "dev"
Requires-Dist: torchvision; extra == "dev"
Requires-Dist: torchaudio; extra == "dev"
Provides-Extra: all
Requires-Dist: RiskLabAI[pde]; extra == "all"
Requires-Dist: RiskLabAI[synth]; extra == "all"
Requires-Dist: RiskLabAI[plot]; extra == "all"
Dynamic: license-file
